interstate_love_song/__init__.py
interstate_love_song/__main__.py
interstate_love_song/_version.py
interstate_love_song/agent.py
interstate_love_song/http.py
interstate_love_song/protocol.py
interstate_love_song/serialization.py
interstate_love_song/session.py
interstate_love_song/settings.py
interstate_love_song/transport.py
interstate_love_song/mapping/__init__.py
interstate_love_song/mapping/base.py
interstate_love_song/plugins/__init__.py
interstate_love_song/plugins/simple.py
interstate_love_song-2.0.4.dist-info/LICENSE.txt
interstate_love_song-2.0.4.dist-info/METADATA
interstate_love_song-2.0.4.dist-info/WHEEL
interstate_love_song-2.0.4.dist-info/entry_points.txt
interstate_love_song-2.0.4.dist-info/top_level.txt
interstate_love_song-2.0.4.dist-info/RECORD
